setup.py
distributions/Binomialdistribution.py
distributions/Gaussiandistribution.py
distributions/Generaldistribution.py
distributions/__init__.py
ud_gbdistributions.egg-info/PKG-INFO
ud_gbdistributions.egg-info/SOURCES.txt
ud_gbdistributions.egg-info/dependency_links.txt
ud_gbdistributions.egg-info/not-zip-safe
ud_gbdistributions.egg-info/top_level.txt